brainbox/__init__.py
brainbox/transforms.py
brainbox/neural/__init__.py
brainbox/neural/correlation.py
brainbox/neural/rdm.py
brainbox/rfs/__init__.py
brainbox/rfs/rfs.py
brainbox/rfs/gabor/__init__.py
brainbox/rfs/gabor/fit.py
brainbox/rfs/gabor/query.py
brainbox/rfs/gaussian/__init__.py
brainbox/rfs/gaussian/fit.py
brainbox/rfs/gaussian/query.py
brainbox/spiking/__init__.py
brainbox/spiking/isi.py
brainbox/spiking/metric.py
brainbox/spiking/rate.py
brainbox/spiking/synchrony.py
brainbox/spiking/util.py
brainbox/tuning/__init__.py
brainbox/tuning/fit.py
brainbox/tuning/query.py
brainbox-0.0.9.dist-info/licenses/LICENSE.md
tests/__init__.py
tests/physiology/__init__.py
tests/physiology/test_spiking.py
tests/physiology/test_util.py
brainbox-0.0.9.dist-info/METADATA
brainbox-0.0.9.dist-info/WHEEL
brainbox-0.0.9.dist-info/top_level.txt
brainbox-0.0.9.dist-info/RECORD
