Metadata-Version: 2.4
Name: brainbox
Version: 0.0.9
Summary: Simplifying the life of a computational neuroscientist.
Home-page: https://github.com/webstorms/BrainBox
Author: Luke Taylor
Author-email: webstorms@gmail.com
Project-URL: Bug Tracker, https://github.com/webstorms/BrainBox/issues
Classifier: Programming Language :: Python :: 3
Classifier: License :: OSI Approved :: MIT License
Classifier: Operating System :: OS Independent
Requires-Python: >=3.8
License-File: LICENSE.md
Requires-Dist: pandas
Requires-Dist: h5py
Requires-Dist: torch
Requires-Dist: torchvision
Requires-Dist: kornia
Requires-Dist: scipy
Requires-Dist: scikit-learn
Dynamic: license-file
